signer_client/__init__.py
signer_client/api_client.py
signer_client/client.py
signer_client/configuration.py
signer_client/rest.py
signer_client/api/__init__.py
signer_client/api/documents_api.py
signer_client/api/flows_api.py
signer_client/api/folders_api.py
signer_client/api/marks_sessions_api.py
signer_client/api/notifications_api.py
signer_client/api/organizations_api.py
signer_client/api/upload_api.py
signer_client/models/__init__.py
signer_client/models/action_status.py
signer_client/models/agent_types.py
signer_client/models/agents_agent_model.py
signer_client/models/api_uploads_body.py
signer_client/models/applications_application_display_model.py
signer_client/models/attachments_attachment_model.py
signer_client/models/attachments_attachment_upload_model.py
signer_client/models/attachments_create_attachment_result.py
signer_client/models/authentication_types.py
signer_client/models/batch_item_result_model.py
signer_client/models/billing_billing_information_model.py
signer_client/models/billing_company_billing_information_model.py
signer_client/models/billing_individual_billing_information_model.py
signer_client/models/billing_information_types.py
signer_client/models/certificate_holder_types.py
signer_client/models/certificate_types.py
signer_client/models/certificates_attribute_certificate_info_model.py
signer_client/models/delete_action.py
signer_client/models/document_download_types.py
signer_client/models/document_filter_status.py
signer_client/models/document_flows_document_flow_create_request.py
signer_client/models/document_flows_document_flow_data.py
signer_client/models/document_flows_document_flow_details_model.py
signer_client/models/document_flows_document_flow_model.py
signer_client/models/document_mark_document_mark_position_model.py
signer_client/models/document_mark_flow_action_position_model.py
signer_client/models/document_mark_marks_session_create_request.py
signer_client/models/document_mark_marks_session_create_response.py
signer_python_client-0.9.0.dist-info/METADATA
signer_python_client-0.9.0.dist-info/WHEEL
signer_python_client-0.9.0.dist-info/top_level.txt
signer_python_client-0.9.0.dist-info/RECORD
