Metadata-Version: 2.4
Name: signer-python-client
Version: 0.9.0
Summary: A Python client library for the Lacuna Signer API
Home-page: https://github.com/lacunasoftware/signer-python-client
Author-email: Lacuna Software <support@lacunasoftware.com>
Maintainer-email: Lacuna Software <support@lacunasoftware.com>
License: MIT
Project-URL: Homepage, https://github.com/LacunaSoftware/SignerPythonClient
Project-URL: Documentation, https://signer-lac.azurewebsites.net/swagger/index.html
Project-URL: Repository, https://github.com/LacunaSoftware/SignerPythonClient
Project-URL: Bug Tracker, https://github.com/LacunaSoftware/SignerPythonClient/issues
Keywords: signer,digital-signature,api-client,lacuna,document-management
Classifier: Development Status :: 4 - Beta
Classifier: Intended Audience :: Developers
Classifier: License :: OSI Approved :: MIT License
Classifier: Operating System :: OS Independent
Classifier: Programming Language :: Python :: 3
Classifier: Programming Language :: Python :: 3.7
Classifier: Programming Language :: Python :: 3.8
Classifier: Programming Language :: Python :: 3.9
Classifier: Programming Language :: Python :: 3.10
Classifier: Programming Language :: Python :: 3.11
Classifier: Topic :: Software Development :: Libraries :: Python Modules
Classifier: Topic :: Office/Business
Requires-Python: >=3.7
Requires-Dist: urllib3>=1.15
Requires-Dist: six>=1.10
Requires-Dist: certifi
Requires-Dist: python-dateutil
Provides-Extra: dev
Requires-Dist: pytest>=6.0; extra == "dev"
Requires-Dist: pytest-cov>=2.0; extra == "dev"
Requires-Dist: black>=21.0; extra == "dev"
Requires-Dist: mypy>=0.800; extra == "dev"
Requires-Dist: flake8>=3.8; extra == "dev"
Dynamic: home-page
